ansurr/__init__.py
ansurr/adjust_text.py
ansurr/ansurr.py
ansurr/compare.py
ansurr/cyrange.py
ansurr/dssp.py
ansurr/export_nef.py
ansurr/functions.py
ansurr/plot2D.py
ansurr/rci_nef.py
ansurr/rci_nef_dicts.py
ansurr/rigidipy.py
ansurr/bin/PANAV.jar
ansurr/bin/__init__.py
ansurr/bin/calc_rigidity_OSX.bin
ansurr/bin/calc_rigidity_gcc4.4.7.bin
ansurr/bin/calc_rigidity_gcc4.8.4.bin
ansurr/bin/cyrange.bin
ansurr/bin/cyrange_OSX.bin
ansurr/bin/dssp.bin
ansurr/lib/__init__.py
ansurr/lib/benchmarks.json
ansurr/lib/distance_cutoffs.txt
ansurr/lib/het_dictionary.txt
ansurr/lib/std_dictionary.txt
ansurr-2.1.2.dist-info/LICENSE
ansurr-2.1.2.dist-info/METADATA
ansurr-2.1.2.dist-info/WHEEL
ansurr-2.1.2.dist-info/entry_points.txt
ansurr-2.1.2.dist-info/top_level.txt
ansurr-2.1.2.dist-info/RECORD
