Metadata-Version: 2.1
Name: ansurr
Version: 2.1.2
Summary: ANSURR uses backbone chemical shifts to validate the accuracy of NMR protein structures.
Home-page: https://github.com/nickjf/ansurr2
Author: Nick J Fowler
Author-email: nickjfowler0@gmail.com
Project-URL: Bug Tracker, https://github.com/nickjf/ansurr2/issues
Classifier: Programming Language :: Python :: 3
Classifier: License :: OSI Approved :: MIT License
Classifier: Operating System :: OS Independent
Requires-Python: >=3.6
License-File: LICENSE
Requires-Dist: numpy
Requires-Dist: scipy
Requires-Dist: matplotlib
Requires-Dist: pynmrstar
